MrAnalyticaOfficial/__init__.py
MrAnalyticaOfficial/phoenix_vision.py
MrAnalyticaOfficial-0.8.7799997.dist-info/METADATA
MrAnalyticaOfficial-0.8.7799997.dist-info/WHEEL
MrAnalyticaOfficial-0.8.7799997.dist-info/top_level.txt
MrAnalyticaOfficial-0.8.7799997.dist-info/RECORD
