Metadata-Version: 2.1
Name: MrAnalyticaOfficial
Version: 0.8.7799997
Summary: Uma biblioteca poderosa para análise de dados, incluindo o módulo PhoenixVision para reconhecimento facial.
Home-page: https://github.com/user/MrAnalyticaOfficial
Author: Matheus Rodrigo
Author-email: mranalytica@mranalytica.com
Classifier: Programming Language :: Python :: 3
Classifier: License :: OSI Approved :: MIT License
Classifier: Operating System :: OS Independent
Requires-Python: >=3.6
Requires-Dist: opencv-python
Requires-Dist: numpy
Requires-Dist: tensorflow
Requires-Dist: scikit-learn
